{"i":{"pKcT6b2oP":{"id":"pKcT6b2oP","type":"slide","setup":{"bord":{"size":0,"rad":0},"bg":{"selectedKey":"image","fill":{"opac":1,"rgb":"var(--TC3)"},"img":{"filt":{"opac":100,"gray":0,"blur":0,"tint":{"rgb":"var(--TC3)","opac":0.5,"blendMode":"multiply"}},"pos":{"type":"crop","fit":{"bg":{"color":{"rgb":"#FFF","opac":100}},"vali":"center","hali":"center"},"crop":{"poi":{"x":557,"y":450}}},"measures":{"size":{"width":1080,"height":591}}}},"transparentBg":{"selectedKey":false}}},"pxBiMboWjU":{"id":"pxBiMboWjU","type":"interactive","subtype":"interactiveRichText","setup":{"frmeTp":{"selectedKey":"bottomLine"},"bg":{"selectedKey":"fill","fill":{"opac":0.2,"rgb":"#FFF"}},"txt":{"val":{"ops":[{"insert":"Economía Circular","attributes":{"color":"var(--TC5)","background":"rgba(0, 0, 0, 0)","bold":true}},{"insert":"\n","attributes":{"size":"large","align":"center"}}]},"rType":"richtext"},"vali":"middle","hali":"","frmeColo":{"color":{"opac":1,"rgb":"var(--TC5)"}}}},"qPs28O4KB-":{"id":"qPs28O4KB-","type":"interactive","subtype":"interactiveImage","setup":{"img":{"filt":{"opac":100,"gray":0,"blur":0,"tint":{"rgb":"#FFF","opac":0}},"pos":{"type":"crop","fit":{"bg":{"color":{"rgb":"#FFF","opac":100},"gradient":{"angle":0,"opac":0.5,"stops":[{"color":"#000000","pos":0},{"color":"#000000","pos":100}]}},"vali":"center","hali":"center","margin":0},"crop":{"bg":{"color":{"rgb":"#FFF","opac":0},"gradient":{"angle":0,"opac":0.5,"stops":[{"color":"#000000","pos":0},{"color":"#000000","pos":100}]}},"poi":{"x":427,"y":453}},"mask":{"shape":1,"bg":{"color":{"rgb":"#FFF","opac":0},"gradient":{"angle":0,"opac":0.5,"stops":[{"color":"#000000","pos":0},{"color":"#000000","pos":100}]}}}},"measures":{"size":{"width":1500,"height":1001}},"orig":{"rType":"asset","rSubType":"image","fileName":"2148884839.jpg","fileSize":604254,"val":"mc-b3f7d6c9a9d4683ce1f67991cf677b64.jpg","aid":"DHwyBpkh5"}},"zoom":{"selectedKey":false}}},"6petdDMG82":{"id":"6petdDMG82","type":"interactive","subtype":"interactiveRichText","setup":{"frmeTp":{"selectedKey":"rightLine"},"bg":{"selectedKey":"fill","fill":{"opac":0.2,"rgb":"#FFF"}},"txt":{"rType":"richtext","val":{"ops":[{"insert":"\n"},{"attributes":{"color":"#000000","background":"rgba(0, 0, 0, 0)"},"insert":"La economía circular proporciona beneficios ambientales y económicos al cerrar los ciclos de materiales y energía, lo que reduce los impactos negativos asociados con la extracción y eliminación de recursos. También fomenta la innovación, crea empleos verdes y mejora la eficiencia en el uso de recursos, lo que resulta en oportunidades económicas significativas."},{"insert":"\n","attributes":{"align":"justify"}}]}},"paddV1":28,"hali":"","vali":"middle","frmeColo":{"color":{"opac":1,"rgb":"var(--TC5)"}}}}},"v":"1"}