{"i":{"Fv8yWD4ob":{"id":"Fv8yWD4ob","type":"slide","setup":{"bg":{"selectedKey":"image","fill":{"opac":1,"rgb":"var(--TC3)"},"img":{"filt":{"opac":100,"gray":0,"blur":0,"tint":{"rgb":"var(--TC3)","opac":0.5,"blendMode":"multiply"}},"pos":{"type":"crop","fit":{"bg":{"color":{"rgb":"#FFF","opac":100}},"vali":"center","hali":"center"},"crop":{"poi":{"x":557,"y":450}}},"measures":{"size":{"width":1080,"height":591}}}},"transparentBg":{"selectedKey":false},"bord":{"size":0,"rad":0}}},"pFkBJvhOXg":{"id":"pFkBJvhOXg","type":"interactive","subtype":"interactiveRichText","setup":{"frmeTp":{"selectedKey":"rightLine"},"bg":{"selectedKey":"fill","fill":{"opac":0.2,"rgb":"#FFF"}},"txt":{"rType":"richtext","val":{"ops":[{"insert":"\n","attributes":{"align":"justify"}},{"attributes":{"background":"rgba(0, 0, 0, 0)","lang":"ES-CO","color":"#000000"},"insert":"Un ejemplo concreto de economía circular en acción es una empresa de moda sostenible que opera bajo los principios de diseño para la circularidad, reutilización y reciclaje de materiales."},{"insert":"\n\n\n","attributes":{"align":"justify"}}]}},"paddV1":18,"hali":"","frmeColo":{"color":{"opac":1,"rgb":"var(--TC5)"}},"vali":"middle"}},"Na58miAP2a":{"id":"Na58miAP2a","type":"interactive","subtype":"interactiveRichText","setup":{"frmeTp":{"selectedKey":"bottomLine"},"bg":{"selectedKey":"fill","fill":{"opac":0.2,"rgb":"var(--TC14)"}},"txt":{"val":{"ops":[{"attributes":{"bold":true,"lang":"ES-CO","color":"var(--TC5)","background":"rgba(0, 0, 0, 0)"},"insert":"Ejemplo de Economía Circular: Empresa de Moda Sostenible"},{"attributes":{"color":"var(--TC5)","background":"rgba(0, 0, 0, 0)"},"insert":" "},{"insert":"\n","attributes":{"size":"large","align":"center"}}]},"rType":"richtext"},"vali":"middle","hali":"","frmeColo":{"color":{"opac":1,"rgb":"var(--TC5)"}}}},"7SCnZypAvw":{"id":"7SCnZypAvw","type":"interactive","subtype":"interactiveImage","setup":{"img":{"filt":{"opac":100,"gray":0,"blur":0,"tint":{"rgb":"#FFF","opac":0}},"pos":{"type":"crop","fit":{"bg":{"color":{"rgb":"#FFF","opac":100},"gradient":{"angle":0,"opac":0.5,"stops":[{"color":"#000000","pos":0},{"color":"#000000","pos":100}]}},"vali":"center","hali":"center"},"crop":{"bg":{"color":{"rgb":"#FFF","opac":0},"gradient":{"angle":0,"opac":0.5,"stops":[{"color":"#000000","pos":0},{"color":"#000000","pos":100}]}},"poi":{"x":3247,"y":2401}},"mask":{"shape":1,"bg":{"color":{"rgb":"#FFF","opac":0},"gradient":{"angle":0,"opac":0.5,"stops":[{"color":"#000000","pos":0},{"color":"#000000","pos":100}]}}},"zoom":0},"measures":{"size":{"width":7036,"height":4696}},"orig":{"rType":"asset","rSubType":"image","fileName":"vecteezy_taller-de-productos-de-cuero_5859418 (1).jpg","fileSize":828119,"val":"mc-c5098153b37db6d9e28dd53a0dda04c1.jpg","aid":"ybR7Hg0Yo"}},"zoom":{"selectedKey":false}}}},"v":"1"}